pythonic_fp/circulararray/__init__.py
pythonic_fp/circulararray/__init__.pyi
pythonic_fp/circulararray/auto.py
pythonic_fp/circulararray/auto.pyi
pythonic_fp/circulararray/fixed.py
pythonic_fp/circulararray/fixed.pyi
pythonic_fp/circulararray/py.typed
pythonic_fp_circulararray-6.0.1.dist-info/licenses/LICENSE
pythonic_fp_circulararray-6.0.1.dist-info/WHEEL
pythonic_fp_circulararray-6.0.1.dist-info/METADATA
pythonic_fp_circulararray-6.0.1.dist-info/RECORD
