Metadata-Version: 2.4
Name: pythonic-fp-circulararray
Version: 6.0.1
Summary: Circular Array
Keywords: auto resizing,circular array,circulararray,dequeue,indexable,pop,push
Author-email: "Geoffrey R. Scheller" <geoffrey@scheller.com>
Requires-Python: >=3.13
Classifier: Development Status :: 5 - Production/Stable
Classifier: Framework :: Pytest
Classifier: Intended Audience :: Developers
Classifier: License :: OSI Approved :: Apache Software License
Classifier: Operating System :: OS Independent
Classifier: Programming Language :: Python :: 3.13
Classifier: Typing :: Typed
License-File: LICENSE
Requires-Dist: pythonic-fp-gadgets>=4.0.2
Requires-Dist: pytest>=8.4.1 ; extra == "test"
Project-URL: Changelog, https://github.com/grscheller/pythonic-fp-circulararray/blob/main/CHANGELOG.rst
Project-URL: Documentation, https://grscheller.github.io/pythonic-fp/circulararray/development/build/html/
Project-URL: Homepage, https://grscheller.github.io/pythonic-fp/homepage/build/html/
Project-URL: Source, https://github.com/grscheller/pythonic-fp-circulararray
Provides-Extra: test
